autosrp/__init__.py
autosrp/admin.py
autosrp/app_settings.py
autosrp/apps.py
autosrp/auth_hooks.py
autosrp/forms.py
autosrp/models.py
autosrp/tasks.py
autosrp/urls.py
autosrp/views.py
autosrp/locale/.gitkeep
autosrp/management/__init__.py
autosrp/management/commands/__init__.py
autosrp/management/commands/autosrp_preload_data.py
autosrp/management/commands/dogma.py
autosrp/management/commands/refresh_item_prices.py
autosrp/migrations/0001_initial.py
autosrp/migrations/0002_alter_appsetting_options_and_more.py
autosrp/migrations/0003_alter_submission_options.py
autosrp/migrations/__init__.py
autosrp/services/__init__.py
autosrp/services/discord.py
autosrp/services/fitcheck.py
autosrp/services/notifications.py
autosrp/services/payouts.py
autosrp/services/penalties.py
autosrp/services/pricing.py
autosrp/services/providers.py
autosrp/services/services_update.py
autosrp/services/users.py
autosrp/services/zkill.py
autosrp/static/autosrp/.gitkeep
autosrp/templates/autosrp/base.html
autosrp/templates/autosrp/index.html
autosrp/templates/autosrp/admin/home.html
autosrp/templates/autosrp/admin/ignored_list.html
autosrp/templates/autosrp/admin/penalty_form.html
autosrp/templates/autosrp/admin/penalty_list.html
autosrp/templates/autosrp/admin/reward_form.html
autosrp/templates/autosrp/admin/reward_list.html
autosrp/templates/autosrp/admin/stats.html
autosrp/templates/autosrp/fc/my_submissions.html
autosrp/templates/autosrp/fc/submit.html
autosrp/templates/autosrp/notifications/alliance_auth_notify.html
autosrp/templates/autosrp/notifications/discord_notify.html
autosrp/templates/autosrp/review/_kill_fit_detail.html
autosrp/templates/autosrp/review/batch_detail.html
autosrp/templates/autosrp/review/batch_list.html
autosrp/templates/autosrp/review/user_landing.html
autosrp/templatetags/form_extras.py
autosrp/templatetags/num.py
autosrp/tests/__init__.py
autosrp/tests/test_example.py
autosrp/views/__init__.py
autosrp/views/admin.py
autosrp/views/fc.py
autosrp/views/review.py
autosrp-0.0.6.dist-info/METADATA
autosrp-0.0.6.dist-info/WHEEL
autosrp-0.0.6.dist-info/licenses/LICENSE
autosrp-0.0.6.dist-info/RECORD
