Metadata-Version: 2.4
Name: autosrp
Version: 0.0.6
Summary: Automatic SRP Review
Project-URL: Changelog, https://github.com/BroodLK/aa-auto-srp/blob/master/CHANGELOG.md
Project-URL: Issue / Bug Reports, https://github.com/BroodLK/aa-auto-srp/issues
Author-email: BioBrute <a@a.com>
License:                     GNU GENERAL PUBLIC LICENSE
License-File: LICENSE
Keywords: allianceauth,autosrp
Classifier: Environment :: Web Environment
Classifier: Framework :: Django
Classifier: Framework :: Django :: 4.2
Classifier: Intended Audience :: Developers
Classifier: License :: OSI Approved :: GNU General Public License v3 (GPLv3)
Classifier: Operating System :: OS Independent
Classifier: Programming Language :: Python
Classifier: Programming Language :: Python :: 3 :: Only
Classifier: Programming Language :: Python :: 3.10
Classifier: Programming Language :: Python :: 3.11
Classifier: Programming Language :: Python :: 3.12
Classifier: Programming Language :: Python :: 3.13
Classifier: Topic :: Internet :: WWW/HTTP
Classifier: Topic :: Internet :: WWW/HTTP :: Dynamic Content
Requires-Python: >=3.10
Requires-Dist: allianceauth<5,>=4.3.1
